Metadata-Version: 2.4
Name: pybloqs
Version: 1.4.3
Summary: Data Visualization and Report Building
Author-email: Man Alpha Technology <ManAlphaTech@man.com>
License:                   GNU LESSER GENERAL PUBLIC LICENSE
Project-URL: Homepage, https://github.com/man-group/pybloqs
Project-URL: Repository, https://github.com/man-group/pybloqs
Project-URL: Documentation, https://pybloqsmain.readthedocs.io/en/latest/
Project-URL: Changelog, https://github.com/man-group/PyBloqs/blob/master/CHANGES.md
Keywords: ahl,pdf,html,visualization,report
Classifier: Operating System :: OS Independent
Classifier: Intended Audience :: Science/Research
Classifier: Programming Language :: Python
Classifier: Topic :: Scientific/Engineering
Classifier: Programming Language :: Python :: 3.8
Classifier: Programming Language :: Python :: 3.9
Classifier: Programming Language :: Python :: 3.10
Classifier: Programming Language :: Python :: 3.11
Classifier: Programming Language :: Python :: 3.12
Requires-Python: >=3.8
License-File: LICENSE
Requires-Dist: beautifulsoup4
Requires-Dist: matplotlib
Requires-Dist: markdown
Requires-Dist: html5lib
Requires-Dist: pandas
Requires-Dist: docutils
Requires-Dist: lxml
Requires-Dist: pyyaml
Requires-Dist: jinja2
Provides-Extra: docs-and-notebook
Requires-Dist: sphinx; extra == "docs-and-notebook"
Requires-Dist: nbsphinx; extra == "docs-and-notebook"
Requires-Dist: ipython[notebook]; extra == "docs-and-notebook"
Requires-Dist: sphinxcontrib-apidoc; extra == "docs-and-notebook"
Provides-Extra: plotly
Requires-Dist: plotly; extra == "plotly"
Requires-Dist: kaleido; extra == "plotly"
Provides-Extra: bokeh
Requires-Dist: bokeh; extra == "bokeh"
Requires-Dist: selenium; extra == "bokeh"
Provides-Extra: tests
Requires-Dist: mock; extra == "tests"
Requires-Dist: pytest; extra == "tests"
Requires-Dist: pytest-cov; extra == "tests"
Provides-Extra: altair
Requires-Dist: altair; extra == "altair"
Provides-Extra: server
Requires-Dist: Flask; extra == "server"
Provides-Extra: code
Requires-Dist: pygments; extra == "code"
Dynamic: license-file
